megaAPI/__init__.py
megaAPI/mobapips.dll
megaAPI/quote.py
megaAPI/uFIISAPI.dll
megaAPI/uFIISAPI.lib
megaSec-1.4.dist-info/METADATA
megaSec-1.4.dist-info/WHEEL
megaSec-1.4.dist-info/top_level.txt
megaSec-1.4.dist-info/RECORD
