Metadata-Version: 2.1
Name: megaSec
Version: 1.4
Summary: MegaSec API
Home-page: https://github.com/cloud3940/megaSec
Author: TZHAN
Author-email: UNKNOWN
License: MIT
Keywords: mega
Platform: UNKNOWN
Classifier: Development Status :: 4 - Beta
Classifier: Environment :: Web Environment
Classifier: Intended Audience :: Developers
Classifier: Intended Audience :: System Administrators
Classifier: License :: OSI Approved :: MIT License
Classifier: Operating System :: Microsoft
Classifier: Programming Language :: Python :: 3.7
Classifier: Topic :: Internet :: Proxy Servers
